LarpixParser/__init__.py
LarpixParser/charge_calibration.py
LarpixParser/coord_transform.py
LarpixParser/event_parser.py
LarpixParser/geom_to_dict.py
LarpixParser/get_charge.py
LarpixParser/get_raw_coord.py
LarpixParser/get_vdrift.py
LarpixParser/hit_parser.py
LarpixParser/units.py
LarpixParser/util.py
LarpixParser/config_repo/2x2.yaml
LarpixParser/config_repo/module0.yaml
LarpixParser/config_repo/multi_tile_layout-2.3.16.yaml
LarpixParser/config_repo/multi_tile_layout-3.0.40.yaml
LarpixParser/config_repo/ndlar-module.yaml
LarpixParser/config_repo/dict_repo/multi_tile_layout-2.3.16.pkl
LarpixParser/config_repo/dict_repo/multi_tile_layout-3.0.40.pkl
LarpixParser-0.0.8.dist-info/LICENSE
LarpixParser-0.0.8.dist-info/METADATA
LarpixParser-0.0.8.dist-info/WHEEL
LarpixParser-0.0.8.dist-info/top_level.txt
LarpixParser-0.0.8.dist-info/RECORD
