Metadata-Version: 2.1
Name: LarpixParser
Version: 0.0.8
Summary: A package parsing the larpix output to hit-level
Home-page: https://github.com/YifanC/larpix_readout_parser
Author: Yifan C. and others
Author-email: cyifan@slac.stanford.edu
Classifier: Development Status :: 2 - Pre-Alpha
Classifier: Intended Audience :: Developers
Classifier: License :: OSI Approved :: MIT License
Classifier: Operating System :: OS Independent
Classifier: Programming Language :: Python :: 3
Classifier: Topic :: Scientific/Engineering :: Physics
Requires-Python: >=3.2
License-File: LICENSE
Requires-Dist: numpy
Requires-Dist: h5py
Requires-Dist: fire
